ai_command_master/__init__.py
ai_command_master/cli.py
ai_command_master/config.py
ai_command_master/core.py
ai_command_master/data_formatter.py
ai_command_master/execution.py
ai_command_master/history.py
ai_command_master/logger.py
ai_command_master/system.py
ai_command_master/utils.py
ai_command_master/api_clients/__init__.py
ai_command_master/api_clients/base.py
ai_command_master/api_clients/deepseek.py
ai_command_master/api_clients/factory.py
ai_command_master/api_clients/moonshot.py
ai_command_master/config/.last_profile
ai_command_master/config/default.yaml
ai_command_master-1.1.3.dist-info/entry_points.txt
ai_command_master-1.1.3.dist-info/licenses/LICENSE
ai_command_master-1.1.3.dist-info/WHEEL
ai_command_master-1.1.3.dist-info/METADATA
ai_command_master-1.1.3.dist-info/RECORD
