Metadata-Version: 2.4
Name: ai_command_master
Version: 1.1.3
Summary: ai command master example
Author-email: EmanYanzhou <yuzilongcc@gmail.com>
Requires-Python: >=3.8
License-File: LICENSE
Requires-Dist: click>=8.1
Requires-Dist: openai>=1.7.3
Requires-Dist: PyYAML>=6.0.2
Requires-Dist: pyperclip>=1.9.0
